jidouqie_mcp_test/__init__.py
jidouqie_mcp_test-0.1.0.dist-info/WHEEL
jidouqie_mcp_test-0.1.0.dist-info/entry_points.txt
jidouqie_mcp_test-0.1.0.dist-info/METADATA
jidouqie_mcp_test-0.1.0.dist-info/RECORD
