Metadata-Version: 2.3
Name: jidouqie-mcp-test
Version: 0.1.0
Summary: Add your description here
Author: djw
Author-email: djw <djwsqc@qq.com>
Requires-Dist: mcp[cli]>=1.13.1
Requires-Python: >=3.13
